{
  "rosso_leggero": [
    {
      "antipasto": [
        "antipasto a base di carne rossa",
        "antipasto a base di carne bianca",
        "salumi affettati"
      ],
      "primo": [
        "primo a base di carne rossa",
        "primo a base di carne bianca"
      ],
      "secondo": [
        "secondo a base di carne rossa"
      ]
    }
  ],
  "rosso_strutturato": [
    {
      "antipasto": [
        "antipasto a base di carne",
        "salumi affettati",
        "formaggi stagionati"
      ],
      "primo": [
        "primo a base di carne rossa",
        "primo a base di sugo di carne"
      ],
      "secondo": [
        "secondo a base di carne rossa"
      ]
    }
  ],
  "bianco_leggero": [
    {
      "antipasto": [
        "antipasto a base di pesce leggero",
        "verdure"
      ],
      "primo": [
        "primo a base di pesce leggero"
      ],
      "secondo": [
        "secondo a base di pesce leggero",
        "secondo a base di carne bianca"
      ]
    }
  ],
  "bianco_strutturato": [
    {
      "antipasto": [
        "antipasto a base di pesce ricco",
        "formaggi freschi"
      ],
      "primo": [
        "primo a base di pesce ricco"
      ],
      "secondo": [
        "secondo a base di pesce ricco",
        "secondo a base di carne bianca"
      ]
    }
  ],
  "ricerca": [],
  "profile": {
    "name": "typicode"
  }
}